{
    "members": [
        {
            "name": "고향집",
            "menu": [
                "순대국",
                "순대정식",
                "순대",
                "국밥"
            ],
            "door": "front",
            "lightly": "yes",
            "alcohol": "no",
            "soup": "yes",
            "spicy": "no",
            "time": 20,
            "lat": 37.58654635775056,
            "lng": 127.04991504870432
        },
        {
            "name": "고향미중식당",
            "menu": [
                "미리팅",
                "마라상궈",
                "꿔바로우",
                "마파두부"
            ],
            "door": "front",
            "lightly": "no",
            "alcohol": "no",
            "soup": "yes",
            "spicy": "yes",
            "time": 10,
            "lat": 37.58654635775056,
            "lng": 127.04991504870432
        },
        {
            "name": "전현필식당",
            "menu": [
                "스테이크",
                "알리오 올리오",
                "파스타",
                "리조또"
            ],
            "door": "front",
            "lightly": "yes",
            "alcohol": "no",
            "soup": "no",
            "spicy": "no",
            "time": 10,
            "lat": 37.578073989298396,
            "lng": 127.04943378896603
        },
        {
            "name": "맘스터치",
            "menu": [
                "햄버거"
            ],
            "door": "front",
            "lightly": "yes",
            "alcohol": "no",
            "soup": "no",
            "spicy": "no",
            "time": 1,
            "lat": 37.583877729654446,
            "lng": 127.05352654127844
        },
        {
            "name": "치쥬",
            "menu": [
                "파니니",
                "파스타",
                "리조또",
                "샐러드",
                "요거트",
                "샌드위치"
            ],
            "door": "front",
            "lightly": "yes",
            "alcohol": "no",
            "soup": "no",
            "spicy": "no",
            "time": 10,
            "lat": 37.583877729654446,
            "lng": 127.05352654127844
        }
    ]
}